__init__.py
grabsampler/__init__.py
grabsampler/sampler.py
grabsampler/sorter/FixedOrdering.py
grabsampler/sorter/MeanBalance.py
grabsampler/sorter/OfflineMeanBalance.py
grabsampler/sorter/PairBalance.py
grabsampler/sorter/RandomReshuffling.py
grabsampler/sorter/SampleWReplacement.py
grabsampler/sorter/ShuffleOnce.py
grabsampler/sorter/SorterBase.py
grabsampler/sorter/__init__.py
grabsampler/sorter/beta/AdaEMABalance.py
grabsampler/sorter/beta/AdaMeanBalance.py
grabsampler/sorter/beta/BatchBalance.py
grabsampler/sorter/beta/EMABalance.py
grabsampler/sorter/beta/NTKBalance.py
grabsampler/sorter/beta/NTKEigen.py
grabsampler/sorter/beta/NTKFixedBalance.py
grabsampler/sorter/beta/NTKFixedEigen.py
grabsampler/sorter/beta/OrderByNorm.py
grabsampler/sorter/beta/RecursiveBalance.py
grabsampler/sorter/beta/RecursivePairBalance.py
grabsampler/sorter/beta/SignBalance.py
grabsampler/sorter/beta/__init__.py
grabsampler/sorter/beta/functional/NTK.py
grabsampler/sorter/beta/functional/__init__.py
grabsampler/utils/EventTimer.py
grabsampler/utils/__init__.py
grabsampler/utils/estimator.py
grabsampler/utils/random_projection/JLGaussianRP.py
grabsampler/utils/random_projection/JLVerySparseRP.py
grabsampler/utils/random_projection/KroneckerRP.py
grabsampler/utils/random_projection/RandomProjection.py
grabsampler/utils/random_projection/__init__.py
grab_sampler-0.1.3.dist-info/LICENSE
grab_sampler-0.1.3.dist-info/METADATA
grab_sampler-0.1.3.dist-info/WHEEL
grab_sampler-0.1.3.dist-info/top_level.txt
grab_sampler-0.1.3.dist-info/RECORD
