Metadata-Version: 2.1
Name: grab-sampler
Version: 0.1.3
Summary: Optimal Permutation-based SGD Data Sampler for PyTorch
Author-email: garywei944 <garywei944@gmail.com>
License: Apache Software License 2.0
Project-URL: Repository, https://github.com/garywei944/grab-sampler
Project-URL: BugTracker, https://github.com/garywei944/grab-sampler/issues
Keywords: GraB,data-permutation,PyTorch,dataloader,sampler
Classifier: Development Status :: 3 - Alpha
Classifier: Intended Audience :: Developers
Classifier: License :: OSI Approved :: Apache Software License
Classifier: Natural Language :: English
Classifier: Operating System :: OS Independent
Classifier: Programming Language :: Python :: 3
Classifier: Programming Language :: Python :: 3.10
Requires-Python: >=3.10
License-File: LICENSE
Requires-Dist: torch >=2.0.0
Requires-Dist: numpy
Requires-Dist: pandas
Requires-Dist: absl-py
Requires-Dist: overrides
Requires-Dist: tqdm
Requires-Dist: scikit-learn
Requires-Dist: torch-sparse
